minchin.releaser-0.9.6-py3.13-nspkg.pth
minchin/releaser/__init__.py
minchin/releaser/constants.py
minchin/releaser/make_release.py
minchin/releaser/util.py
minchin/releaser/vendorize.py
minchin/releaser/__pycache__/__init__.cpython-313.pyc
minchin/releaser/__pycache__/constants.cpython-313.pyc
minchin/releaser/__pycache__/make_release.cpython-313.pyc
minchin/releaser/__pycache__/util.cpython-313.pyc
minchin/releaser/__pycache__/vendorize.cpython-313.pyc
minchin/releaser/_vendor/__init__.py
minchin/releaser/_vendor/text.py
minchin/releaser/_vendor/__pycache__/__init__.cpython-313.pyc
minchin/releaser/_vendor/__pycache__/text.cpython-313.pyc
minchin/releaser/test/__init__.py
minchin/releaser/test/test_setup.py
minchin/releaser/test/__pycache__/__init__.cpython-313.pyc
minchin/releaser/test/__pycache__/test_setup.cpython-313.pyc
minchin_releaser-0.9.6.dist-info/licenses/LICENSE.txt
minchin_releaser-0.9.6.dist-info/METADATA
minchin_releaser-0.9.6.dist-info/WHEEL
minchin_releaser-0.9.6.dist-info/namespace_packages.txt
minchin_releaser-0.9.6.dist-info/top_level.txt
minchin_releaser-0.9.6.dist-info/RECORD
