Metadata-Version: 2.4
Name: minchin.releaser
Version: 0.9.6
Summary: Minchin.Releaser is a collection of tools designed to make releasing Python packages easier.
Home-page: https://github.com/MinchinWeb/minchin.releaser
Author: William Minchin
Author-email: w_minchin@hotmail.com
License: MIT License
Project-URL: Bug Tracker, https://github.com/MinchinWeb/minchin.releaser/issues
Project-URL: Changelog, https://github.com/MinchinWeb/minchin.releaser/blob/master/changelog.rst
Platform: any
Classifier: Development Status :: 4 - Beta
Classifier: Programming Language :: Python :: 3
Classifier: Programming Language :: Python :: 3.8
Classifier: Programming Language :: Python :: 3.9
Classifier: Programming Language :: Python :: 3.10
Classifier: Programming Language :: Python :: 3.11
Classifier: Programming Language :: Python :: 3.12
Classifier: Programming Language :: Python :: 3.13
Classifier: Programming Language :: Python :: 3 :: Only
Classifier: Natural Language :: English
Classifier: Intended Audience :: Developers
Classifier: Operating System :: OS Independent
Classifier: Topic :: Software Development :: Libraries :: Python Modules
Classifier: License :: OSI Approved :: MIT License
License-File: LICENSE.txt
Requires-Dist: colorama>=0.2.5
Requires-Dist: gitpython>=3.1.41
Requires-Dist: invoke>=2.0.0
Requires-Dist: isort>=5
Requires-Dist: semantic_version
Requires-Dist: setuptools
Requires-Dist: twine>=5.0.0
Requires-Dist: wheel>=0.38.1
Requires-Dist: build
Requires-Dist: pkginfo>=1.12.0
Requires-Dist: bleach>=3.3.0
Requires-Dist: certifi>=2024.7.4
Requires-Dist: idna>=3.7
Requires-Dist: pygments>=2.15.0
Requires-Dist: requests>=2.32.4
Requires-Dist: urllib3>=2.5.0
Requires-Dist: zipp>=3.19.1
Provides-Extra: build
Requires-Dist: pip-tools; extra == "build"
Provides-Extra: docs
Provides-Extra: test
Provides-Extra: all
Requires-Dist: pip-tools; extra == "all"
Dynamic: author
Dynamic: author-email
Dynamic: classifier
Dynamic: description
Dynamic: description-content-type
Dynamic: home-page
Dynamic: license
Dynamic: license-file
Dynamic: platform
Dynamic: project-url
Dynamic: provides-extra
Dynamic: requires-dist
Dynamic: summary
